netargparse/__init__.py
netargparse/message.py
netargparse/netargparse.py
netargparse/py.typed
netargparse/server.py
netargparse-2.0.1.dist-info/LICENSE
netargparse-2.0.1.dist-info/METADATA
netargparse-2.0.1.dist-info/WHEEL
netargparse-2.0.1.dist-info/RECORD
