Metadata-Version: 2.3
Name: netargparse
Version: 2.0.1
Summary: Enhance ArgumentParser with a TCP-based API for argument handling.
License: BSD-3-Clause
Author: Kevin Golob
Author-email: 151143873+kvnglb@users.noreply.github.com
Requires-Python: >=3.9,<4.0
Classifier: Development Status :: 5 - Production/Stable
Classifier: Environment :: Console
Classifier: License :: OSI Approved :: BSD License
Classifier: Operating System :: OS Independent
Classifier: Programming Language :: Python :: 3
Classifier: Programming Language :: Python :: 3.9
Classifier: Programming Language :: Python :: 3.10
Classifier: Programming Language :: Python :: 3.11
Classifier: Programming Language :: Python :: 3.12
Classifier: Programming Language :: Python :: 3.13
Classifier: Programming Language :: Python :: 3 :: Only
Classifier: Typing :: Typed
Project-URL: Documentation, https://github.com/kvnglb/netargparse/tree/main/docs
Project-URL: Homepage, https://github.com/kvnglb/netargparse
Project-URL: Repository, https://github.com/kvnglb/netargparse
